Workbook
Name NativeTimeline_Order_Date: #N/A
Name Slicer_Months__Order_Date: #N/A
Name Slicer_Product_Category: #N/A
Name Slicer_Region: #N/A

Sheet Dashboard
A31: Key Insights — Sales Dashboard
A35: 1. Total Sales: ₹1,95,218 | Total Profit: ₹68,287 (35% margin) across 200 orders, 13 months
A37: 2.West region leads at ₹44,084; East trails at ₹32,442 — a 26% performance gap
A39: 3. Books is the top category (₹47,002); Office Supplies is weakest (₹28,631)
A41: 4. September 2024 was peak month (₹20,534); April 2025 dropped sharply (₹3,212) — needs verification (may be incomplete data)
A43: 5. 10 of 27 customers (37%) drive most of the revenue — top customer: James Wilson (₹20,775)
A45: 6. Every ₹1 in sales adds ₹0.35 in profit, with sales explaining ~60% of profit variation (R² = 0.60)

Sheet data
A1: Customer_ID | B1: Customer_Name | C1: Region | D1: Product_Category | E1: Sales | F1: Quantity | G1: Discount | H1: Order_Date | I1: Profit
A2: CUST019 | B2: James Davis | C2: West | D2: Books | E2: 1036.09 | F2: 4 | G2: 0.2 | H2: 45392 | I2: 331.55
A3: CUST012 | B3: Robert Anderson | C3: West | D3: Clothing | E3: 1101.28 | F3: 3 | G3: 0.2 | H3: 45393 | I3: 440.51
A4: CUST017 | B4: James Taylor | C4: East | D4: Books | E4: 713.34 | F4: 17 | G4: 0 | H4: 45396 | I4: 285.34
A5: CUST005 | B5: Robert Anderson | C5: South | D5: Electronics | E5: 760.93 | F5: 4 | G5: 0.15 | H5: 45396 | I5: 161.7
A6: CUST030 | B6: James Wilson | C6: North | D6: Books | E6: 847 | F6: 12 | G6: 0.2 | H6: 45397 | I6: 271.04
A7: CUST007 | B7: Michael Anderson | C7: North | D7: Furniture | E7: 965.64 | F7: 8 | G7: 0.1 | H7: 45398 | I7: 304.18
A8: CUST001 | B8: Linda Wilson | C8: West | D8: Electronics | E8: 1317.53 | F8: 12 | G8: 0.05 | H8: 45398 | I8: 312.91
A9: CUST026 | B9: Mary Davis | C9: East | D9: Furniture | E9: 1074.47 | F9: 6 | G9: 0.2 | H9: 45401 | I9: 300.85
A10: CUST009 | B10: Linda Jackson | C10: Central | D10: Books | E10: 501.54 | F10: 11 | G10: 0.05 | H10: 45401 | I10: 190.59
A11: CUST010 | B11: David Thomas | C11: Central | D11: Clothing | E11: 737.31 | F11: 2 | G11: 0.05 | H11: 45401 | I11: 350.22
A12: CUST014 | B12: Emma Davis | C12: West | D12: Office Supplies | E12: 1572.82 | F12: 6 | G12: 0.05 | H12: 45402 | I12: 672.38
A13: CUST014 | B13: David Thomas | C13: Central | D13: Books | E13: 1343.13 | F13: 14 | G13: 0.15 | H13: 45404 | I13: 456.66
... A201: CUST016 | B201: David Thomas | C201: South | D201: Clothing | E201: 928.32 | F201: 2 | G201: 0.05 | H201: 45754 | I201: 440.95

Sheet Top 10
E1: Q1. Apply conditional formatting to highlight top 10 customers based on total purchase.
E2: customer ID | F2: Customer Name | G2: Order Count | H2: Total Quanitiy | I2: Total Sales | J2: Total Profit | K2: Avg Discount | L2: Q7. Hight Value Customer | M2: Q6. TimeStamp
E3: CUST001 | F3: David Anderson | G3: =COUNTIF(data!$B$2:$B$201,F3) -> 6 | H3: =SUMIF(data!$B$2:$B$201, F3, data!$F$2:$F$201) -> 45 | I3: =SUMIF(data!$B$2:$B$201, F3, data!$E$2:$E$201) -> 5465.71 | J3: =SUMIF(data!$B$2:$B$201, F3, data!$I$2:$I$201) -> 1937.85 | K3: =ROUND(AVERAGEIF(data!$B$2:$B$201, F3, data!$G$2:$G$201)*100, 0) -> 15 | L3: =IF(RANK(I3, $I$3:$I$29,0)<=10, "YES", "NO") -> NO | M3: =NOW() -> 46280.596
E4: CUST002 | F4: David Brown | G4: =COUNTIF(data!$B$2:$B$201,F4) -> 13 | H4: =SUMIF(data!$B$2:$B$201, F4, data!$F$2:$F$201) -> 119 | I4: =SUMIF(data!$B$2:$B$201, F4, data!$E$2:$E$201) -> 11915.83 | J4: =SUMIF(data!$B$2:$B$201, F4, data!$I$2:$I$201) -> 4061.91 | K4: =ROUND(AVERAGEIF(data!$B$2:$B$201, F4, data!$G$2:$G$201)*100, 0) -> 5 | L4: =IF(RANK(I4, $I$3:$I$29,0)<=10, "YES", "NO") -> YES | M4: =NOW() -> 46280.596
E5: CUST003 | F5: David Davis | G5: =COUNTIF(data!$B$2:$B$201,F5) -> 4 | H5: =SUMIF(data!$B$2:$B$201, F5, data!$F$2:$F$201) -> 50 | I5: =SUMIF(data!$B$2:$B$201, F5, data!$E$2:$E$201) -> 3819.14 | J5: =SUMIF(data!$B$2:$B$201, F5, data!$I$2:$I$201) -> 1273.19 | K5: =ROUND(AVERAGEIF(data!$B$2:$B$201, F5, data!$G$2:$G$201)*100, 0) -> 14 | L5: =IF(RANK(I5, $I$3:$I$29,0)<=10, "YES", "NO") -> NO | M5: =NOW() -> 46280.596
E6: CUST004 | F6: David Smith | G6: =COUNTIF(data!$B$2:$B$201,F6) -> 2 | H6: =SUMIF(data!$B$2:$B$201, F6, data!$F$2:$F$201) -> 30 | I6: =SUMIF(data!$B$2:$B$201, F6, data!$E$2:$E$201) -> 1672.88 | J6: =SUMIF(data!$B$2:$B$201, F6, data!$I$2:$I$201) -> 569.64 | K6: =ROUND(AVERAGEIF(data!$B$2:$B$201, F6, data!$G$2:$G$201)*100, 0) -> 13 | L6: =IF(RANK(I6, $I$3:$I$29,0)<=10, "YES", "NO") -> NO | M6: =NOW() -> 46280.596
E7: CUST005 | F7: David Thomas | G7: =COUNTIF(data!$B$2:$B$201,F7) -> 7 | H7: =SUMIF(data!$B$2:$B$201, F7, data!$F$2:$F$201) -> 47 | I7: =SUMIF(data!$B$2:$B$201, F7, data!$E$2:$E$201) -> 7020.38 | J7: =SUMIF(data!$B$2:$B$201, F7, data!$I$2:$I$201) -> 2919.45 | K7: =ROUND(AVERAGEIF(data!$B$2:$B$201, F7, data!$G$2:$G$201)*100, 0) -> 9 | L7: =IF(RANK(I7, $I$3:$I$29,0)<=10, "YES", "NO") -> NO | M7: =NOW() -> 46280.596
E8: CUST006 | F8: Emma Davis | G8: =COUNTIF(data!$B$2:$B$201,F8) -> 12 | H8: =SUMIF(data!$B$2:$B$201, F8, data!$F$2:$F$201) -> 122 | I8: =SUMIF(data!$B$2:$B$201, F8, data!$E$2:$E$201) -> 11398.32 | J8: =SUMIF(data!$B$2:$B$201, F8, data!$I$2:$I$201) -> 3846.93 | K8: =ROUND(AVERAGEIF(data!$B$2:$B$201, F8, data!$G$2:$G$201)*100, 0) -> 8 | L8: =IF(RANK(I8, $I$3:$I$29,0)<=10, "YES", "NO") -> YES | M8: =NOW() -> 46280.596
E9: CUST007 | F9: Emma Taylor | G9: =COUNTIF(data!$B$2:$B$201,F9) -> 5 | H9: =SUMIF(data!$B$2:$B$201, F9, data!$F$2:$F$201) -> 54 | I9: =SUMIF(data!$B$2:$B$201, F9, data!$E$2:$E$201) -> 5014.96 | J9: =SUMIF(data!$B$2:$B$201, F9, data!$I$2:$I$201) -> 1909.57 | K9: =ROUND(AVERAGEIF(data!$B$2:$B$201, F9, data!$G$2:$G$201)*100, 0) -> 6 | L9: =IF(RANK(I9, $I$3:$I$29,0)<=10, "YES", "NO") -> NO | M9: =NOW() -> 46280.596
E10: CUST008 | F10: Emma Wilson | G10: =COUNTIF(data!$B$2:$B$201,F10) -> 8 | H10: =SUMIF(data!$B$2:$B$201, F10, data!$F$2:$F$201) -> 94 | I10: =SUMIF(data!$B$2:$B$201, F10, data!$E$2:$E$201) -> 8543.97 | J10: =SUMIF(data!$B$2:$B$201, F10, data!$I$2:$I$201) -> 2718.84 | K10: =ROUND(AVERAGEIF(data!$B$2:$B$201, F10, data!$G$2:$G$201)*100, 0) -> 9 | L10: =IF(RANK(I10, $I$3:$I$29,0)<=10, "YES", "NO") -> YES | M10: =NOW() -> 46280.596
E11: CUST009 | F11: James Davis | G11: =COUNTIF(data!$B$2:$B$201,F11) -> 6 | H11: =SUMIF(data!$B$2:$B$201, F11, data!$F$2:$F$201) -> 54 | I11: =SUMIF(data!$B$2:$B$201, F11, data!$E$2:$E$201) -> 6255.7 | J11: =SUMIF(data!$B$2:$B$201, F11, data!$I$2:$I$201) -> 2122.82 | K11: =ROUND(AVERAGEIF(data!$B$2:$B$201, F11, data!$G$2:$G$201)*100, 0) -> 9 | L11: =IF(RANK(I11, $I$3:$I$29,0)<=10, "YES", "NO") -> NO | M11: =NOW() -> 46280.596
E12: CUST010 | F12: James Taylor | G12: =COUNTIF(data!$B$2:$B$201,F12) -> 6 | H12: =SUMIF(data!$B$2:$B$201, F12, data!$F$2:$F$201) -> 66 | I12: =SUMIF(data!$B$2:$B$201, F12, data!$E$2:$E$201) -> 5615.28 | J12: =SUMIF(data!$B$2:$B$201, F12, data!$I$2:$I$201) -> 2203.68 | K12: =ROUND(AVERAGEIF(data!$B$2:$B$201, F12, data!$G$2:$G$201)*100, 0) -> 8 | L12: =IF(RANK(I12, $I$3:$I$29,0)<=10, "YES", "NO") -> NO | M12: =NOW() -> 46280.596
E13: CUST011 | F13: James Wilson | G13: =COUNTIF(data!$B$2:$B$201,F13) -> 20 | H13: =SUMIF(data!$B$2:$B$201, F13, data!$F$2:$F$201) -> 236 | I13: =SUMIF(data!$B$2:$B$201, F13, data!$E$2:$E$201) -> 20774.74 | J13: =SUMIF(data!$B$2:$B$201, F13, data!$I$2:$I$201) -> 7077.92 | K13: =ROUND(AVERAGEIF(data!$B$2:$B$201, F13, data!$G$2:$G$201)*100, 0) -> 13 | L13: =IF(RANK(I13, $I$3:$I$29,0)<=10, "YES", "NO") -> YES | M13: =NOW() -> 46280.596
E14: CUST012 | F14: John Brown | G14: =COUNTIF(data!$B$2:$B$201,F14) -> 2 | H14: =SUMIF(data!$B$2:$B$201, F14, data!$F$2:$F$201) -> 23 | I14: =SUMIF(data!$B$2:$B$201, F14, data!$E$2:$E$201) -> 1450.99 | J14: =SUMIF(data!$B$2:$B$201, F14, data!$I$2:$I$201) -> 410.92 | K14: =ROUND(AVERAGEIF(data!$B$2:$B$201, F14, data!$G$2:$G$201)*100, 0) -> 5 | L14: =IF(RANK(I14, $I$3:$I$29,0)<=10, "YES", "NO") -> NO | M14: =NOW() -> 46280.596
... E29: CUST027 | F29: Sarah Davis | G29: =COUNTIF(data!$B$2:$B$201,F29) -> 6 | H29: =SUMIF(data!$B$2:$B$201, F29, data!$F$2:$F$201) -> 48 | I29: =SUMIF(data!$B$2:$B$201, F29, data!$E$2:$E$201) -> 5771.59 | J29: =SUMIF(data!$B$2:$B$201, F29, data!$I$2:$I$201) -> 2039.74 | K29: =ROUND(AVERAGEIF(data!$B$2:$B$201, F29, data!$G$2:$G$201)*100, 0) -> 12 | L29: =IF(RANK(I29, $I$3:$I$29,0)<=10, "YES", "NO") -> NO | M29: =NOW() -> 46280.596

Sheet What-If
A1: Q2. What-If Analysis - Change Of Total Profit On Discount
A3: Current Data | D3: Discount Rate | E3: Projected Total Profit | F3: New Vs Current
A4: Current Average Discount | B4: =AVERAGE(data[Discount]) -> 0.09725 | D4: 0 | E4: =SUM($B$5*(1-D4)-($B$5*(1-$B$4)-$B$6)) -> 87271.937 | F4: =E4-$B$6 -> 18984.927
A5: Current Total Sales | B5: =SUM(data[Sales]) -> 195217.76 | D5: 0.05 | E5: =SUM($B$5*(1-D5)-($B$5*(1-$B$4)-$B$6)) -> 77511.049 | F5: =E5-$B$6 -> 9224.0392
A6: current Total Profit | B6: =SUM(data[Profit]) -> 68287.01 | D6: 0.1 | E6: =SUM($B$5*(1-D6)-($B$5*(1-$B$4)-$B$6)) -> 67750.161 | F6: =E6-$B$6 -> -536.84884
D7: 0.15 | E7: =SUM($B$5*(1-D7)-($B$5*(1-$B$4)-$B$6)) -> 57989.273 | F7: =E7-$B$6 -> -10297.737
A8: What-If Data | D8: 0.2 | E8: =SUM($B$5*(1-D8)-($B$5*(1-$B$4)-$B$6)) -> 48228.385 | F8: =E8-$B$6 -> -20058.625
A9: New Average Discount | B9: 0.11 | D9: 0.25 | E9: =SUM($B$5*(1-D9)-($B$5*(1-$B$4)-$B$6)) -> 38467.497 | F9: =E9-$B$6 -> -29819.513
A10: Total Profit at New Discount | B10: =SUM(B5*(1-$B$9)-(B5*(1-B4)-B6)) -> 65797.984 | D10: 0.3 | E10: =SUM($B$5*(1-D10)-($B$5*(1-$B$4)-$B$6)) -> 28706.609 | F10: =E10-$B$6 -> -39580.401
A11: New Vs Current Profit | B11: =B10-B6 -> -2489.0264

Sheet Regression & Statistics
A1: Q3. Linear Regression Of (Profit Vs Sales) | K1: Q4. Descriptive Statistics
A2: Regression Statistics | K2: Statistics | L2: Sales | M2: Profit
A3: Multiple R | B3: 0.77356566 | K3: Mean | L3: 975.78729 | M3: 341.48472
A4: R Square | B4: 0.59840384 | K4: Standard Error | L4: 21.266301 | M4: 9.6483541
A5: Adjusted R Square | B5: 0.59636528 | K5: Median | L5: 973.26 | M5: 332.32
A6: Standard Error | B6: 86.471707 | K6: Mode | L6: - | M6: -
A7: Observations | B7: 199 | K7: Standard Deviation | L7: 299.99809 | M7: 136.10678
K8: Sample Variance | L8: 89998.856 | M8: 18525.057
K9: Kurtosis | L9: -0.10144708 | M9: 0.24746466
B10: df | C10: SS | D10: MS | E10: F | F10: Significance F | K10: Skewness | L10: 0.14954552 | M10: 0.57090181
A11: Regression | B11: 1 | C11: 2194922.1 | D11: 2194922.1 | E11: 293.54254 | F11: 6.8782376e-41 | K11: Range | L11: 1665.15 | M11: 704.83
A12: Residual | B12: 197 | C12: 1473039.2 | D12: 7477.3561 | K12: Minimum | L12: 258.51 | M12: 64.63
A13: Total | B13: 198 | C13: 3667961.2 | K13: Maximum | L13: 1923.66 | M13: 769.46
K14: Sum | L14: 194181.67 | M14: 67955.46
B15: Coefficients | C15: Standard Error | D15: t Stat | E15: P-value | F15: Lower 95% | G15: Upper 95% | H15: Lower 95.0% | I15: Upper 95.0% | K15: Count | L15: 199 | M15: 199
A16: Intercept | B16: -0.97824545 | C16: 20.907198 | D16: -0.046789889 | E16: 0.96272809 | F16: -42.208891 | G16: 40.2524 | H16: -42.208891 | I16: 40.2524
A17: 1036.09 | B17: 0.35096068 | C17: 0.020484386 | D17: 17.133083 | E17: 6.8782376e-41 | F17: 0.31056385 | G17: 0.39135751 | H17: 0.31056385 | I17: 0.39135751

Sheet Monthy Sales
A1: Q5. Monthy Sales Growth | E1: Line Chart
A2: Row Labels | B2: Sum of Sales | C2: Sales Growth
A3: 2024 | B3: 145429.36 | C3: NA
A4: Apr | B4: 19029.96 | C4: -
A5: May | B5: 18507.34 | C5: =(B5-B4)/B4 -> -0.027463011
A6: Jun | B6: 20187.51 | C6: =(B6-B5)/B5 -> 0.090783981
A7: Jul | B7: 11609.04 | C7: =(B7-B6)/B6 -> -0.42493948
A8: Aug | B8: 10091.7 | C8: =(B8-B7)/B7 -> -0.13070331
A9: Sep | B9: 20533.5 | C9: =(B9-B8)/B8 -> 1.0346919
A10: Oct | B10: 14215.24 | C10: =(B10-B9)/B9 -> -0.30770497
A11: Nov | B11: 20135.03 | C11: =(B11-B10)/B10 -> 0.41643968
A12: Dec | B12: 11120.04 | C12: =(B12-B11)/B11 -> -0.44772667
A13: 2025 | B13: 49788.4 | C13: NA
A14: Jan | B14: 14914.65 | C14: =(B14-B12)/B12 -> 0.34124068
A15: Feb | B15: 14006.36 | C15: =(B15-B14)/B14 -> -0.060899183
A16: Mar | B16: 17655.22 | C16: =(B16-B15)/B15 -> 0.26051451
A17: Apr | B17: 3212.17 | C17: =(B17-B16)/B16 -> -0.81806117
A18: Grand Total | B18: 195217.76 | C18: NA

Sheet Total Sales
A1: Q8. Total Sales By Product Category And Region (Pivot Table) | I1: Multi_Bar Chart
A2: Total Sales | B2: Region
A3: Product_Category | B3: Central | C3: East | D3: North | E3: South | F3: West | G3: Grand Total
A4: Books | B4: 11297.15 | C4: 11389.09 | D4: 8037.01 | E4: 9588.04 | F4: 6691.17 | G4: 47002.46
A5: Clothing | B5: 12200.26 | C5: 2401.45 | D5: 8422.82 | E5: 8393.63 | F5: 10509.43 | G5: 41927.59
A6: Electronics | B6: 6621.24 | C6: 2869.54 | D6: 8191.71 | E6: 11989.07 | F6: 11372.44 | G6: 41044
A7: Furniture | B7: 4876.96 | C7: 7592.34 | D7: 6978.08 | E7: 7982.73 | F7: 9182.78 | G7: 36612.89
A8: Office Supplies | B8: 8472.72 | C8: 8189.22 | D8: 3345.8 | E8: 2295.32 | F8: 6327.76 | G8: 28630.82
A9: Grand Total | B9: 43468.33 | C9: 32441.64 | D9: 34975.42 | E9: 40248.79 | F9: 44083.58 | G9: 195217.76
A12: Row Labels | B12: Sum of Quantity
A13: Central | B13: 410
A14: East | B14: 374
A15: North | B15: 383
A16: South | B16: 374
A17: West | B17: 458
A18: Grand Total | B18: 1999
